core_dev/__init__.py
core_dev/__main__.py
core_dev/_builtins.py
core_dev/_collections/BinaryTree.py
core_dev/_collections/BlockChain.py
core_dev/_collections/LinkedList.py
core_dev/_collections/__init__.py
core_dev/_collections/_dict/__init__.py
core_dev/_collections/_dict/_dict.py
core_dev/_collections/_dict/exceptions.py
core_dev/_collections/_list/__init__.py
core_dev/_collections/_list/_list.py
core_dev/_collections/_list/exceptions.py
core_dev/_collections/graph/__init__.py
core_dev/_collections/graph/edges.json
core_dev/_collections/graph/exceptions.py
core_dev/_collections/graph/graph.py
core_dev/_collections/graph/tests/__test__.py
core_dev/_collections/queue.py
core_dev/_collections/stack.py
core_dev/_curses/NCursesApplication.py
core_dev/_curses/__init__.py
core_dev/_curses/_curses.py
core_dev/_curses/_screen.py
core_dev/_json/__init__.py
core_dev/_json/_json.py
core_dev/_logging/__init__.py
core_dev/_logging/_logging.py
core_dev/_logging/load_config.py
core_dev/_logging/logging.conf
core_dev/_logging/logging.yaml
core_dev/_math/__init__.py
core_dev/_math/__main__.py
core_dev/_math/_math.py
core_dev/_requests.py
core_dev/_rich/__init__.py
core_dev/_rich/__main__.py
core_dev/_rich/_rich.py
core_dev/_string.py
core_dev/_time.py
core_dev/_tkinter/ColorsWindow.py
core_dev/_tkinter/__init__.py
core_dev/_tkinter/colors.png
core_dev/_tkinter/configs.py
core_dev/_tkinter/objects.py
core_dev/_yaml.py
core_dev/_zip.py
core_dev/aesthetics.py
core_dev/algorithms/__init__.py
core_dev/algorithms/backtracking.py
core_dev/animations/__init__.py
core_dev/animations/__main__.py
core_dev/animations/animations.py
core_dev/animations/progress.py
core_dev/animations/spinners.py
core_dev/audio.py
core_dev/crypto__.py
core_dev/datetime_/__init__.py
core_dev/datetime_/__main__.py
core_dev/datetime_/datetime_.py
core_dev/decorators.py
core_dev/download.py
core_dev/drive.py
core_dev/email__.py
core_dev/encryption.py
core_dev/exa.py
core_dev/exceptions.py
core_dev/icons.py
core_dev-0.2.1.dist-info/LICENSE
core_dev-0.2.1.dist-info/WHEEL
core_dev-0.2.1.dist-info/METADATA
core_dev-0.2.1.dist-info/RECORD
