Metadata-Version: 2.1
Name: core-dev
Version: 0.2.1
Summary: 
Home-page: https://github.com/alexzanderr/_core-dev
License: MIT
Author: alexzanderr
Author-email: alexxander18360@gmail.com
Requires-Python: >=3.10,<4.0
Classifier: Environment :: Console
Classifier: Framework :: Flake8
Classifier: License :: OSI Approved :: MIT License
Classifier: Operating System :: OS Independent
Classifier: Programming Language :: Python :: 3
Classifier: Programming Language :: Python :: 3.10
Classifier: Topic :: Software Development :: Documentation
Classifier: Topic :: Software Development :: Libraries :: Python Modules
Classifier: Topic :: Software Development :: Quality Assurance
Requires-Dist: MouseInfo (>=0.1.3,<0.2.0)
Requires-Dist: Pillow (>=9.0.1,<10.0.0)
Requires-Dist: PyAudio (>=0.2.11,<0.3.0)
Requires-Dist: PyAutoGUI (>=0.9.53,<0.10.0)
Requires-Dist: PyGetWindow (>=0.0.9,<0.0.10)
Requires-Dist: PyMsgBox (>=1.0.9,<2.0.0)
Requires-Dist: PyPDF2 (>=1.26.0,<2.0.0)
Requires-Dist: PyRect (>=0.1.4,<0.2.0)
Requires-Dist: PyScreeze (>=0.1.28,<0.2.0)
Requires-Dist: PySocks (>=1.7.1,<2.0.0)
Requires-Dist: PyYAML (>=6.0,<7.0)
Requires-Dist: Pygments (>=2.11.2,<3.0.0)
Requires-Dist: SpeechRecognition (>=3.8.1,<4.0.0)
Requires-Dist: Wand (>=0.6.7,<0.7.0)
Requires-Dist: appdirs (>=1.4.4,<2.0.0)
Requires-Dist: astroid (>=2.9.3,<3.0.0)
Requires-Dist: async_generator (>=1.10,<2.0)
Requires-Dist: attrs (>=21.4.0,<22.0.0)
Requires-Dist: beautifulsoup4 (>=4.10.0,<5.0.0)
Requires-Dist: bs4 (>=0.0.1,<0.0.2)
Requires-Dist: certifi (>=2021.10.8,<2022.0.0)
Requires-Dist: cffi (>=1.15.0,<2.0.0)
Requires-Dist: chardet (>=4.0.0,<5.0.0)
Requires-Dist: charset-normalizer (>=2.0.11,<3.0.0)
Requires-Dist: click (>=8.0.3,<9.0.0)
Requires-Dist: colorama (>=0.4.4,<0.5.0)
Requires-Dist: commonmark (>=0.9.1,<0.10.0)
Requires-Dist: coverage (>=6.3.1,<7.0.0)
Requires-Dist: coverage-badge (>=1.1.0,<2.0.0)
Requires-Dist: cryptography (>=36.0.1,<37.0.0)
Requires-Dist: cycler (>=0.11.0,<0.12.0)
Requires-Dist: datedelta (>=1.4,<2.0)
Requires-Dist: decopatch (>=1.4.8,<2.0.0)
Requires-Dist: decorator (>=5.1.1,<6.0.0)
Requires-Dist: docstr-coverage (>=2.1.1,<3.0.0)
Requires-Dist: execnet (>=1.9.0,<2.0.0)
Requires-Dist: ffmpeg-python (>=0.2.0,<0.3.0)
Requires-Dist: fonttools (>=4.29.1,<5.0.0)
Requires-Dist: future (>=0.18.2,<0.19.0)
Requires-Dist: gTTS (>=2.2.3,<3.0.0)
Requires-Dist: geojson (>=2.5.0,<3.0.0)
Requires-Dist: greenlet (>=1.1.2,<2.0.0)
Requires-Dist: h11 (>=0.13.0,<0.14.0)
Requires-Dist: idna (>=3.3,<4.0)
Requires-Dist: imageio (>=2.15.0,<3.0.0)
Requires-Dist: imageio-ffmpeg (>=0.4.5,<0.5.0)
Requires-Dist: importlib-metadata (>=4.10.1,<5.0.0)
Requires-Dist: iniconfig (>=1.1.1,<2.0.0)
Requires-Dist: isort (>=5.10.1,<6.0.0)
Requires-Dist: jedi (>=0.18.1,<0.19.0)
Requires-Dist: keyboard (>=0.13.5,<0.14.0)
Requires-Dist: kiwisolver (>=1.3.2,<2.0.0)
Requires-Dist: lazy-object-proxy (>=1.7.1,<2.0.0)
Requires-Dist: makefun (>=1.13.1,<2.0.0)
Requires-Dist: matplotlib (>=3.5.1,<4.0.0)
Requires-Dist: mccabe (>=0.7.0,<0.8.0)
Requires-Dist: numpy (>=1.22.2,<2.0.0)
Requires-Dist: opencv-python (>=4.5.5,<5.0.0)
Requires-Dist: outcome (>=1.1.0,<2.0.0)
Requires-Dist: packaging (>=21.3,<22.0)
Requires-Dist: parso (>=0.8.3,<0.9.0)
Requires-Dist: pdfminer.six (>=20211012,<20211013)
Requires-Dist: pdfplumber (>=0.6.0,<0.7.0)
Requires-Dist: platformdirs (>=2.4.1,<3.0.0)
Requires-Dist: playsound (>=1.3.0,<2.0.0)
Requires-Dist: playwright (>=1.18.2,<2.0.0)
Requires-Dist: pluggy (>=1.0.0,<2.0.0)
Requires-Dist: proglog (>=0.1.9,<0.2.0)
Requires-Dist: prompt-toolkit (>=3.0.27,<4.0.0)
Requires-Dist: ptpython (>=3.0.20,<4.0.0)
Requires-Dist: py (>=1.11.0,<2.0.0)
Requires-Dist: pyOpenSSL (>=22.0.0,<23.0.0)
Requires-Dist: pycparser (>=2.21,<3.0)
Requires-Dist: pydub (>=0.25.1,<0.26.0)
Requires-Dist: pyowm (>=3.2.0,<4.0.0)
Requires-Dist: pyparsing (>=3.0.7,<4.0.0)
Requires-Dist: pyperclip (>=1.8.2,<2.0.0)
Requires-Dist: pyppeteer (>=1.0.2,<2.0.0)
Requires-Dist: pytesseract (>=0.3.8,<0.4.0)
Requires-Dist: pytest (>=7.0.0,<8.0.0)
Requires-Dist: pytest-cases (>=3.6.8,<4.0.0)
Requires-Dist: pytest-forked (>=1.4.0,<2.0.0)
Requires-Dist: pytest-steps (>=1.8.0,<2.0.0)
Requires-Dist: pytest-xdist (>=2.5.0,<3.0.0)
Requires-Dist: python-dateutil (>=2.8.2,<3.0.0)
Requires-Dist: python-nmap (>=0.7.1,<0.8.0)
Requires-Dist: python3-nmap (>=1.5.1,<2.0.0)
Requires-Dist: python3-xlib (>=0.15,<0.16)
Requires-Dist: pyttsx3 (>=2.90,<3.0)
Requires-Dist: pytweening (>=1.0.4,<2.0.0)
Requires-Dist: pytz (>=2021.3,<2022.0)
Requires-Dist: pyzbar (>=0.1.8,<0.2.0)
Requires-Dist: requests (>=2.27.1,<3.0.0)
Requires-Dist: rich (>=11.1.0,<12.0.0)
Requires-Dist: selenium (>=4.1.0,<5.0.0)
Requires-Dist: setuptools (>=60.8.1,<61.0.0)
Requires-Dist: simplejson (>=3.17.6,<4.0.0)
Requires-Dist: six (>=1.16.0,<2.0.0)
Requires-Dist: sniffio (>=1.2.0,<2.0.0)
Requires-Dist: sortedcontainers (>=2.4.0,<3.0.0)
Requires-Dist: sounddevice (>=0.4.4,<0.5.0)
Requires-Dist: soupsieve (>=2.3.1,<3.0.0)
Requires-Dist: stackprinter (>=0.2.5,<0.3.0)
Requires-Dist: sudo (>=1.0.0,<2.0.0)
Requires-Dist: toml (>=0.10.2,<0.11.0)
Requires-Dist: tqdm (>=4.62.3,<5.0.0)
Requires-Dist: trio (>=0.19.0,<0.20.0)
Requires-Dist: trio-websocket (>=0.9.2,<0.10.0)
Requires-Dist: urllib3 (>=1.26.8,<2.0.0)
Requires-Dist: wcwidth (>=0.2.5,<0.3.0)
Requires-Dist: websockets (>=10.1,<11.0)
Requires-Dist: wrapt (>=1.13.3,<2.0.0)
Requires-Dist: wsproto (>=1.0.0,<2.0.0)
Requires-Dist: zipp (>=3.7.0,<4.0.0)
Project-URL: Repository, https://github.com/alexzanderr/_core-dev
